kinyarwanda/__init__.py
kinyarwanda/cli.py
kinyarwanda/template/cookiecutter.json
kinyarwanda/template/{{cookiecutter.project_slug}}/README.md
kinyarwanda/template/{{cookiecutter.project_slug}}/main.py
kinyarwanda/ururimi_rwacu/README.md
kinyarwanda/ururimi_rwacu/main.py
kinyarwanda-0.1.0.dist-info/METADATA
kinyarwanda-0.1.0.dist-info/WHEEL
kinyarwanda-0.1.0.dist-info/entry_points.txt
kinyarwanda-0.1.0.dist-info/RECORD
