Metadata-Version: 2.3
Name: kinyarwanda
Version: 0.1.0
Summary: A simple command-line tool that leverages cookiecutter scaffolding package
Author: Asaph Irabaruta
Author-email: asaph.irabaruta@ansys.com
Requires-Python: >=3.10
Classifier: Programming Language :: Python :: 3
Classifier: Programming Language :: Python :: 3.10
Classifier: Programming Language :: Python :: 3.11
Classifier: Programming Language :: Python :: 3.12
Classifier: Programming Language :: Python :: 3.13
Requires-Dist: click (==8.1.3)
Requires-Dist: cookiecutter (>=2.6.0,<3.0.0)
